vb_pdftopng/__init__.py
vb_pdftopng/__main__.py
vb_pdftopng/functions_pdf.py
vb_pdftopng/main.py
vb_pdftopng-0.1.6.dist-info/METADATA
vb_pdftopng-0.1.6.dist-info/WHEEL
vb_pdftopng-0.1.6.dist-info/entry_points.txt
vb_pdftopng-0.1.6.dist-info/RECORD
