Metadata-Version: 2.1
Name: vb-pdftopng
Version: 0.1.6
Summary: Added show default=True for every options
Author: vaibhavblayer
Author-email: vaibhavblayer@gmail.com
Requires-Python: >=3.11,<4.0
Classifier: Programming Language :: Python :: 3
Classifier: Programming Language :: Python :: 3.11
Requires-Dist: pdf2image (>=1.16.3,<2.0.0)
